fugle_marketdata/__init__.py
fugle_marketdata/client_factory.py
fugle_marketdata/constants.py
fugle_marketdata/rest/__init__.py
fugle_marketdata/rest/base_rest.py
fugle_marketdata/rest/factory.py
fugle_marketdata/rest/futopt/__init__.py
fugle_marketdata/rest/futopt/client.py
fugle_marketdata/rest/futopt/historical.py
fugle_marketdata/rest/futopt/intraday.py
fugle_marketdata/rest/stock/__init__.py
fugle_marketdata/rest/stock/client.py
fugle_marketdata/rest/stock/historical.py
fugle_marketdata/rest/stock/intraday.py
fugle_marketdata/rest/stock/snapshot.py
fugle_marketdata/rest/stock/technical.py
fugle_marketdata/websocket/__init__.py
fugle_marketdata/websocket/client.py
fugle_marketdata/websocket/factory.py
fugle_marketdata/websocket/futopt/__init__.py
fugle_marketdata/websocket/futopt/client.py
fugle_marketdata/websocket/stock/__init__.py
fugle_marketdata/websocket/stock/client.py
fugle_marketdata-2.3.0.dist-info/LICENSE
fugle_marketdata-2.3.0.dist-info/METADATA
fugle_marketdata-2.3.0.dist-info/WHEEL
fugle_marketdata-2.3.0.dist-info/RECORD
