Metadata-Version: 2.1
Name: fugle-marketdata
Version: 2.3.0
Summary: Fugle Realtime API 1.0 client library for Python
Home-page: https://github.com/fugle-dev/fugle-realtime-py#readme
License: MIT
Keywords: fugle,realtime,stock
Author: Fortuna Intelligence Co., Ltd.
Author-email: development@fugle.tw
Requires-Python: >=3.7,<4.0
Classifier: License :: OSI Approved :: MIT License
Classifier: Programming Language :: Python :: 3
Classifier: Programming Language :: Python :: 3.7
Classifier: Programming Language :: Python :: 3.8
Classifier: Programming Language :: Python :: 3.9
Classifier: Programming Language :: Python :: 3.10
Classifier: Programming Language :: Python :: 3.11
Classifier: Programming Language :: Python :: 3.12
Requires-Dist: pyee (>=11.1.0,<12.0.0) ; python_full_version > "3.11.0"
Requires-Dist: pyee (>=9.0.4,<10.0.0) ; python_full_version <= "3.11.0"
Requires-Dist: requests (>=2.28.2,<3.0.0)
Requires-Dist: websocket-client (>=1.5.1,<2.0.0)
Project-URL: Documentation, https://developer.fugle.tw
Project-URL: Repository, https://github.com/fugle-dev/fugle-realtime-py
